gene_expression.py
gene_expression-0.0.2.dist-info/METADATA
gene_expression-0.0.2.dist-info/WHEEL
gene_expression-0.0.2.dist-info/licenses/LICENSE
gene_expression-0.0.2.dist-info/RECORD
